pyfindvs/__init__.py
pyfindvs/_find_vs2015.py
pyfindvs/_find_winsdk.py
pyfindvs/_helper.cp37-win_amd64.pyd
pyfindvs/reghelper.py
pyfindvs/msbuildcompiler/__init__.py
pyfindvs/msbuildcompiler/compiler.py
pyfindvs/msbuildcompiler/enable_msbuildcompiler.py
pyfindvs/msbuildcompiler/options.py
pyfindvs/msbuildcompiler/template.py
pyfindvs/msbuildcompiler/vcxproj.template
pyfindvs-0.6.291.dist-info/METADATA
pyfindvs-0.6.291.dist-info/RECORD
pyfindvs-0.6.291.dist-info/WHEEL
pyfindvs-0.6.291.dist-info/entry_points.txt
pyfindvs-0.6.291.dist-info/top_level.txt
