Metadata-Version: 1.1
Name: pyfindvs
Version: 0.6.291
Summary: Python module for locating Visual Studio
Home-page: https://github.com/zooba/pyfindvs
Author: Microsoft Corporation
Author-email: python@microsoft.com
License: UNKNOWN
Platform: UNKNOWN
Classifier: Development Status :: 4 - Beta
Classifier: Environment :: Win32 (MS Windows)
Classifier: License :: OSI Approved :: MIT License
Classifier: Natural Language :: English
Classifier: Operating System :: Microsoft :: Windows
Classifier: Programming Language :: Python
Classifier: Programming Language :: Python :: 3.6
Classifier: Programming Language :: Python :: 3.7
Classifier: Programming Language :: Python :: 3 :: Only
